{"id":"27a4a62d-3bdc-4512-bc8c-b74cb44b201b","platform":"Sooqr","type":"Functional","key":"__sqra","domain":"Advertiser's website domain","i18n":{"en":"Tracks the user's interaction with the website's search-bar-function. This data can be used to present the user with relevant products or services.","fr":"Suivre l'interaction de l'utilisateur avec la fonction de recherche de recherche du site Web. Ces données peuvent être utilisées pour présenter l'utilisateur à des produits ou services pertinents."}}