{"id":"256c7f04-d881-11e9-8a34-2a2ae2dbcce4","platform":"Facebook","type":"Marketing","key":"locale","domain":"facebook.com (3rd party)","i18n":{"en":"This cookie contains the display locale of the last logged in user on this browser. This cookie\nappears to only be set after the user logs out.\nThe locale cookie has a lifetime of one week.","fr":"Ce cookie contient l'affichage local de la dernière utilisateur connectée sur ce navigateur. Ce cookie \n semble seulement être défini après que l'utilisateur se déconnecte. \n Le cookie locale a une vie d'une semaine."}}